./.gitignore
./.markdownlint.json
./.mcp.json
./.pre-commit-config.yaml
./.release-please-manifest.json
./CHANGELOG.md
./LICENSE
./PKG-INFO
./README.md
./opencode.json
./pyproject.toml
./uv.lock
./.github/CODEOWNERS
./.github/dependabot.yml
./.github/workflows/ci.yml
./.github/workflows/dependency-review.yml
./.github/workflows/publish.yml
./.github/workflows/release-please.yml
./agtk/__init__.py
./agtk/cli.py
./agtk/hookspecs.py
./agtk/plugins.py
./agtk/types.py
./docs/create_toolkits.md
./docs/tool_plugin.md
./tests/__init__.py
./tests/conftest.py
./tests/test_fastmcp.py
./tests/test_fastmcp_toolkitsuite.py
./tests/test_tool.py
./tests/test_tool_arg_over_parse.py
./tests/test_toolkit.py
./tests/test_toolkitsuite.py
./tests/test_types.py
./tests/integration/__init__.py
./tests/integration/conftest.py
./tests/integration/test_anthropic_tool_use.py
./tests/integration/test_litellm_tool_use.py
./tests/integration/test_openai_tool_use.py
./tests/integration/test_types_integration.py
agtk-0.1.1.dist-info/METADATA
agtk-0.1.1.dist-info/WHEEL
agtk-0.1.1.dist-info/entry_points.txt
agtk-0.1.1.dist-info/licenses/LICENSE
agtk-0.1.1.dist-info/RECORD
