Metadata-Version: 2.4
Name: agtk
Version: 0.1.1
Summary: agtk (Agent Toolkit)
Project-URL: Homepage, https://github.com/Joilence/agent-toolkits
Project-URL: Repository, https://github.com/Joilence/agent-toolkits
Project-URL: Bug Tracker, https://github.com/Joilence/agent-toolkits/issues
Author: Jonathan Yang
License: MIT License
License-File: LICENSE
Keywords: agent,agentic,llm,mcp
Classifier: Development Status :: 3 - Alpha
Classifier: Intended Audience :: Developers
Classifier: License :: OSI Approved :: MIT License
Classifier: Operating System :: OS Independent
Classifier: Programming Language :: Python :: 3
Classifier: Programming Language :: Python :: 3.12
Classifier: Programming Language :: Python :: 3.13
Classifier: Topic :: Software Development :: Build Tools
Classifier: Topic :: Utilities
Requires-Python: <3.14,>=3.12
Requires-Dist: anthropic>=0.51.0
Requires-Dist: fastmcp>=2.11.1
Requires-Dist: openai>=1.79.0
Requires-Dist: pip>=25.1.1
Requires-Dist: pluggy>=1.5.0
